{
  "version": 2,
  "extractor": "papercropper",
  "tables": [
    {
      "url": "assets/tables/arxiv/2607.16387v1/table-001.webp",
      "caption": "",
      "page": 0,
      "index": 1,
      "width": 1440,
      "height": 337,
      "label": "Table"
    },
    {
      "url": "assets/tables/arxiv/2607.16387v1/table-002.webp",
      "caption": "",
      "page": 0,
      "index": 2,
      "width": 1302,
      "height": 277,
      "label": "Table"
    },
    {
      "url": "assets/tables/arxiv/2607.16387v1/table-003.webp",
      "caption": "",
      "page": 0,
      "index": 3,
      "width": 1411,
      "height": 333,
      "label": "Table"
    },
    {
      "url": "assets/tables/arxiv/2607.16387v1/table-004.webp",
      "caption": "",
      "page": 0,
      "index": 4,
      "width": 727,
      "height": 258,
      "label": "Table"
    },
    {
      "url": "assets/tables/arxiv/2607.16387v1/table-005.webp",
      "caption": "",
      "page": 0,
      "index": 5,
      "width": 938,
      "height": 278,
      "label": "Table"
    },
    {
      "url": "assets/tables/arxiv/2607.16387v1/table-006.webp",
      "caption": "",
      "page": 0,
      "index": 6,
      "width": 1116,
      "height": 209,
      "label": "Table"
    },
    {
      "url": "assets/tables/arxiv/2607.16387v1/table-007.webp",
      "caption": "",
      "page": 0,
      "index": 7,
      "width": 1296,
      "height": 278,
      "label": "Table"
    },
    {
      "url": "assets/tables/arxiv/2607.16387v1/table-008.webp",
      "caption": "",
      "page": 0,
      "index": 8,
      "width": 1379,
      "height": 278,
      "label": "Table"
    },
    {
      "url": "assets/tables/arxiv/2607.16387v1/table-009.webp",
      "caption": "",
      "page": 0,
      "index": 9,
      "width": 1051,
      "height": 350,
      "label": "Table"
    },
    {
      "url": "assets/tables/arxiv/2607.16387v1/table-010.webp",
      "caption": "",
      "page": 0,
      "index": 10,
      "width": 1425,
      "height": 316,
      "label": "Table"
    },
    {
      "url": "assets/tables/arxiv/2607.16387v1/table-011.webp",
      "caption": "",
      "page": 0,
      "index": 11,
      "width": 1208,
      "height": 422,
      "label": "Table"
    },
    {
      "url": "assets/tables/arxiv/2607.16387v1/table-012.webp",
      "caption": "",
      "page": 0,
      "index": 12,
      "width": 1286,
      "height": 171,
      "label": "Table"
    },
    {
      "url": "assets/tables/arxiv/2607.16387v1/table-013.webp",
      "caption": "",
      "page": 0,
      "index": 13,
      "width": 1054,
      "height": 208,
      "label": "Table"
    },
    {
      "url": "assets/tables/arxiv/2607.16387v1/table-014.webp",
      "caption": "",
      "page": 0,
      "index": 14,
      "width": 836,
      "height": 276,
      "label": "Table"
    },
    {
      "url": "assets/tables/arxiv/2607.16387v1/table-015.webp",
      "caption": "",
      "page": 0,
      "index": 15,
      "width": 783,
      "height": 243,
      "label": "Table"
    },
    {
      "url": "assets/tables/arxiv/2607.16387v1/table-016.webp",
      "caption": "",
      "page": 0,
      "index": 16,
      "width": 1131,
      "height": 295,
      "label": "Table"
    },
    {
      "url": "assets/tables/arxiv/2607.16387v1/table-017.webp",
      "caption": "",
      "page": 0,
      "index": 17,
      "width": 1090,
      "height": 170,
      "label": "Table"
    },
    {
      "url": "assets/tables/arxiv/2607.16387v1/table-018.webp",
      "caption": "",
      "page": 0,
      "index": 18,
      "width": 635,
      "height": 166,
      "label": "Table"
    },
    {
      "url": "assets/tables/arxiv/2607.16387v1/table-019.webp",
      "caption": "",
      "page": 0,
      "index": 19,
      "width": 928,
      "height": 207,
      "label": "Table"
    },
    {
      "url": "assets/tables/arxiv/2607.16387v1/table-020.webp",
      "caption": "",
      "page": 0,
      "index": 20,
      "width": 1575,
      "height": 368,
      "label": "Table"
    },
    {
      "url": "assets/tables/arxiv/2607.16387v1/table-021.webp",
      "caption": "",
      "page": 0,
      "index": 21,
      "width": 1583,
      "height": 370,
      "label": "Table"
    },
    {
      "url": "assets/tables/arxiv/2607.16387v1/table-022.webp",
      "caption": "",
      "page": 0,
      "index": 22,
      "width": 1131,
      "height": 207,
      "label": "Table"
    },
    {
      "url": "assets/tables/arxiv/2607.16387v1/table-023.webp",
      "caption": "",
      "page": 0,
      "index": 23,
      "width": 1609,
      "height": 278,
      "label": "Table"
    },
    {
      "url": "assets/tables/arxiv/2607.16387v1/table-024.webp",
      "caption": "",
      "page": 0,
      "index": 24,
      "width": 1107,
      "height": 243,
      "label": "Table"
    },
    {
      "url": "assets/tables/arxiv/2607.16387v1/table-025.webp",
      "caption": "",
      "page": 0,
      "index": 25,
      "width": 1446,
      "height": 780,
      "label": "Table"
    },
    {
      "url": "assets/tables/arxiv/2607.16387v1/table-026.webp",
      "caption": "",
      "page": 0,
      "index": 26,
      "width": 1060,
      "height": 245,
      "label": "Table"
    },
    {
      "url": "assets/tables/arxiv/2607.16387v1/table-027.webp",
      "caption": "",
      "page": 0,
      "index": 27,
      "width": 1259,
      "height": 421,
      "label": "Table"
    },
    {
      "url": "assets/tables/arxiv/2607.16387v1/table-028.webp",
      "caption": "",
      "page": 0,
      "index": 28,
      "width": 1203,
      "height": 208,
      "label": "Table"
    },
    {
      "url": "assets/tables/arxiv/2607.16387v1/table-029.webp",
      "caption": "",
      "page": 0,
      "index": 29,
      "width": 1218,
      "height": 206,
      "label": "Table"
    },
    {
      "url": "assets/tables/arxiv/2607.16387v1/table-030.webp",
      "caption": "",
      "page": 0,
      "index": 30,
      "width": 1341,
      "height": 886,
      "label": "Table"
    },
    {
      "url": "assets/tables/arxiv/2607.16387v1/table-031.webp",
      "caption": "",
      "page": 0,
      "index": 31,
      "width": 1406,
      "height": 492,
      "label": "Table"
    },
    {
      "url": "assets/tables/arxiv/2607.16387v1/table-032.webp",
      "caption": "",
      "page": 0,
      "index": 32,
      "width": 639,
      "height": 206,
      "label": "Table"
    },
    {
      "url": "assets/tables/arxiv/2607.16387v1/table-033.webp",
      "caption": "",
      "page": 0,
      "index": 33,
      "width": 948,
      "height": 759,
      "label": "Table"
    },
    {
      "url": "assets/tables/arxiv/2607.16387v1/table-034.webp",
      "caption": "",
      "page": 0,
      "index": 34,
      "width": 1095,
      "height": 207,
      "label": "Table"
    }
  ]
}