{
  "version": 2,
  "extractor": "papercropper",
  "tables": [
    {
      "url": "assets/tables/arxiv/2607.11149v1/table-001.webp",
      "caption": "",
      "page": 0,
      "index": 1,
      "width": 1849,
      "height": 727,
      "label": "Table"
    },
    {
      "url": "assets/tables/arxiv/2607.11149v1/table-002.webp",
      "caption": "",
      "page": 0,
      "index": 2,
      "width": 886,
      "height": 387,
      "label": "Table"
    },
    {
      "url": "assets/tables/arxiv/2607.11149v1/table-003.webp",
      "caption": "",
      "page": 0,
      "index": 3,
      "width": 887,
      "height": 908,
      "label": "Table"
    },
    {
      "url": "assets/tables/arxiv/2607.11149v1/table-004.webp",
      "caption": "",
      "page": 0,
      "index": 4,
      "width": 883,
      "height": 393,
      "label": "Table"
    },
    {
      "url": "assets/tables/arxiv/2607.11149v1/table-005.webp",
      "caption": "",
      "page": 0,
      "index": 5,
      "width": 884,
      "height": 392,
      "label": "Table"
    },
    {
      "url": "assets/tables/arxiv/2607.11149v1/table-006.webp",
      "caption": "",
      "page": 0,
      "index": 6,
      "width": 885,
      "height": 389,
      "label": "Table"
    },
    {
      "url": "assets/tables/arxiv/2607.11149v1/table-007.webp",
      "caption": "",
      "page": 0,
      "index": 7,
      "width": 886,
      "height": 442,
      "label": "Table"
    },
    {
      "url": "assets/tables/arxiv/2607.11149v1/table-008.webp",
      "caption": "",
      "page": 0,
      "index": 8,
      "width": 885,
      "height": 263,
      "label": "Table"
    },
    {
      "url": "assets/tables/arxiv/2607.11149v1/table-009.webp",
      "caption": "",
      "page": 0,
      "index": 9,
      "width": 883,
      "height": 206,
      "label": "Table"
    },
    {
      "url": "assets/tables/arxiv/2607.11149v1/table-010.webp",
      "caption": "",
      "page": 0,
      "index": 10,
      "width": 884,
      "height": 355,
      "label": "Table"
    },
    {
      "url": "assets/tables/arxiv/2607.11149v1/table-011.webp",
      "caption": "",
      "page": 0,
      "index": 11,
      "width": 888,
      "height": 353,
      "label": "Table"
    },
    {
      "url": "assets/tables/arxiv/2607.11149v1/table-012.webp",
      "caption": "",
      "page": 0,
      "index": 12,
      "width": 885,
      "height": 389,
      "label": "Table"
    },
    {
      "url": "assets/tables/arxiv/2607.11149v1/table-013.webp",
      "caption": "",
      "page": 0,
      "index": 13,
      "width": 887,
      "height": 355,
      "label": "Table"
    },
    {
      "url": "assets/tables/arxiv/2607.11149v1/table-014.webp",
      "caption": "",
      "page": 0,
      "index": 14,
      "width": 886,
      "height": 355,
      "label": "Table"
    },
    {
      "url": "assets/tables/arxiv/2607.11149v1/table-015.webp",
      "caption": "",
      "page": 0,
      "index": 15,
      "width": 885,
      "height": 281,
      "label": "Table"
    },
    {
      "url": "assets/tables/arxiv/2607.11149v1/table-016.webp",
      "caption": "",
      "page": 0,
      "index": 16,
      "width": 884,
      "height": 352,
      "label": "Table"
    },
    {
      "url": "assets/tables/arxiv/2607.11149v1/table-017.webp",
      "caption": "",
      "page": 0,
      "index": 17,
      "width": 887,
      "height": 318,
      "label": "Table"
    },
    {
      "url": "assets/tables/arxiv/2607.11149v1/table-018.webp",
      "caption": "",
      "page": 0,
      "index": 18,
      "width": 884,
      "height": 386,
      "label": "Table"
    }
  ]
}